Workbook

Sheet Inputs
A1: Two-Wheeler Loan Comparison — Inputs
A3: Lender | B3: Principal (₹) | C3: Annual Interest Rate | D3: Tenure (Months) | E3: Processing Fee (₹) | G3: Lender | H3: EMI (₹) | I3: Total Payment (₹) | J3: Total Interest (₹)
A4: HDFC Bank | B4: 400000 | C4: 0.095 | D4: 36 | E4: 4000 | G4: =A4 -> HDFC Bank | H4: =-PMT(C4/12,D4,B4) -> 12813.18 | I4: =H4*D4 -> 461274.48 | J4: =I4-B4 -> 61274.476
A5: ICICI Bank | B5: 400000 | C5: 0.0975 | D5: 36 | E5: 3500 | G5: =A5 -> ICICI Bank | H5: =-PMT(C5/12,D5,B5) -> 12859.976 | I5: =H5*D5 -> 462959.15 | J5: =I5-B5 -> 62959.151
A6: State Bank of India | B6: 400000 | C6: 0.0925 | D6: 36 | E6: 3000 | G6: =A6 -> State Bank of India | H6: =-PMT(C6/12,D6,B6) -> 12766.485 | I6: =H6*D6 -> 459593.48 | J6: =I6-B6 -> 59593.475
A7: Bajaj Finance | B7: 400000 | C7: 0.115 | D7: 36 | E7: 5000 | G7: =A7 -> Bajaj Finance | H7: =-PMT(C7/12,D7,B7) -> 13190.403 | I7: =H7*D7 -> 474854.49 | J7: =I7-B7 -> 74854.493
A8: Aprilia Dealer Finance | B8: 400000 | C8: 0.1025 | D8: 36 | E8: 2500 | G8: =A8 -> Aprilia Dealer Finance | H8: =-PMT(C8/12,D8,B8) -> 12953.875 | I8: =H8*D8 -> 466339.51 | J8: =I8-B8 -> 66339.508
A10: Assumption: Loan amount reflects an on-road price of ~₹4,00,000 for a mid-capacity motorcycle (e.g. Aprilia Tuono 457). Interest rates are illustrative 2026 two-wheeler loan offers for comparison purposes, not live market quotes.

Sheet Amortization
A1: EMI Amortization Schedule | H1: Total Interest (No Prepayment) | I1: =D46 -> 61274.47
H2: Total Payment (No Prepayment) | I2: =C46 -> 461274.48
A3: Select Lender: | B3: HDFC Bank | D3: Principal (₹) | E3: =INDEX(Inputs!$B$4:$B$8,MATCH($B$3,Inputs!$A$4:$A$8,0)) -> 400000
D4: Annual Rate | E4: =INDEX(Inputs!$C$4:$C$8,MATCH($B$3,Inputs!$A$4:$A$8,0)) -> 0.095
D5: Tenure (Months) | E5: =INDEX(Inputs!$D$4:$D$8,MATCH($B$3,Inputs!$A$4:$A$8,0)) -> 36
D6: Monthly EMI (₹) | E6: =-PMT(E4/12,E5,E3) -> 12813.18
A8: Month | B8: Opening Balance (₹) | C8: EMI (₹) | D8: Interest (₹) | E8: Principal (₹) | F8: Closing Balance (₹)
A9: 1 | B9: =$E$3 -> 400000 | C9: =$E$6 -> 12813.18 | D9: =ROUND(B9*$E$4/12,2) -> 3166.67 | E9: =C9-D9 -> 9646.5099 | F9: =MAX(B9-E9,0) -> 390353.49
A10: =A9+1 -> 2 | B10: =F9 -> 390353.49 | C10: =$E$6 -> 12813.18 | D10: =ROUND(B10*$E$4/12,2) -> 3090.3 | E10: =C10-D10 -> 9722.8799 | F10: =MAX(B10-E10,0) -> 380630.61
A11: =A10+1 -> 3 | B11: =F10 -> 380630.61 | C11: =$E$6 -> 12813.18 | D11: =ROUND(B11*$E$4/12,2) -> 3013.33 | E11: =C11-D11 -> 9799.8499 | F11: =MAX(B11-E11,0) -> 370830.76
A12: =A11+1 -> 4 | B12: =F11 -> 370830.76 | C12: =$E$6 -> 12813.18 | D12: =ROUND(B12*$E$4/12,2) -> 2935.74 | E12: =C12-D12 -> 9877.4399 | F12: =MAX(B12-E12,0) -> 360953.32
A13: =A12+1 -> 5 | B13: =F12 -> 360953.32 | C13: =$E$6 -> 12813.18 | D13: =ROUND(B13*$E$4/12,2) -> 2857.55 | E13: =C13-D13 -> 9955.6299 | F13: =MAX(B13-E13,0) -> 350997.69
A14: =A13+1 -> 6 | B14: =F13 -> 350997.69 | C14: =$E$6 -> 12813.18 | D14: =ROUND(B14*$E$4/12,2) -> 2778.73 | E14: =C14-D14 -> 10034.45 | F14: =MAX(B14-E14,0) -> 340963.24
A15: =A14+1 -> 7 | B15: =F14 -> 340963.24 | C15: =$E$6 -> 12813.18 | D15: =ROUND(B15*$E$4/12,2) -> 2699.29 | E15: =C15-D15 -> 10113.89 | F15: =MAX(B15-E15,0) -> 330849.35
A16: =A15+1 -> 8 | B16: =F15 -> 330849.35 | C16: =$E$6 -> 12813.18 | D16: =ROUND(B16*$E$4/12,2) -> 2619.22 | E16: =C16-D16 -> 10193.96 | F16: =MAX(B16-E16,0) -> 320655.39
A17: =A16+1 -> 9 | B17: =F16 -> 320655.39 | C17: =$E$6 -> 12813.18 | D17: =ROUND(B17*$E$4/12,2) -> 2538.52 | E17: =C17-D17 -> 10274.66 | F17: =MAX(B17-E17,0) -> 310380.73
A18: =A17+1 -> 10 | B18: =F17 -> 310380.73 | C18: =$E$6 -> 12813.18 | D18: =ROUND(B18*$E$4/12,2) -> 2457.18 | E18: =C18-D18 -> 10356 | F18: =MAX(B18-E18,0) -> 300024.73
A19: =A18+1 -> 11 | B19: =F18 -> 300024.73 | C19: =$E$6 -> 12813.18 | D19: =ROUND(B19*$E$4/12,2) -> 2375.2 | E19: =C19-D19 -> 10437.98 | F19: =MAX(B19-E19,0) -> 289586.75
A20: =A19+1 -> 12 | B20: =F19 -> 289586.75 | C20: =$E$6 -> 12813.18 | D20: =ROUND(B20*$E$4/12,2) -> 2292.56 | E20: =C20-D20 -> 10520.62 | F20: =MAX(B20-E20,0) -> 279066.13
A21: =A20+1 -> 13 | B21: =F20 -> 279066.13 | C21: =$E$6 -> 12813.18 | D21: =ROUND(B21*$E$4/12,2) -> 2209.27 | E21: =C21-D21 -> 10603.91 | F21: =MAX(B21-E21,0) -> 268462.22
... A44: =A43+1 -> 36 | B44: =F43 -> 12712.534 | C44: =$E$6 -> 12813.18 | D44: =ROUND(B44*$E$4/12,2) -> 100.64 | E44: =C44-D44 -> 12712.54 | F44: =MAX(B44-E44,0) -> 0
A46: Totals | C46: =SUM(C9:C44) -> 461274.48 | D46: =SUM(D9:D44) -> 61274.47 | E46: =SUM(E9:E44) -> 400000.01

Sheet Prepayment Simulator
A1: Prepayment Simulator — What-If Analysis
A3: Select Lender: | B3: HDFC Bank | D3: Principal (₹) | E3: =INDEX(Inputs!$B$4:$B$8,MATCH($B$3,Inputs!$A$4:$A$8,0)) -> 400000
D4: Annual Rate | E4: =INDEX(Inputs!$C$4:$C$8,MATCH($B$3,Inputs!$A$4:$A$8,0)) -> 0.095
A5: Prepayment Amount (₹): | B5: 20000 | D5: Tenure (Months) | E5: =INDEX(Inputs!$D$4:$D$8,MATCH($B$3,Inputs!$A$4:$A$8,0)) -> 36
A6: Prepayment Month: | B6: 6 | D6: Monthly EMI (₹) | E6: =-PMT(E4/12,E5,E3) -> 12813.18
A9: Month | B9: Opening Balance (₹) | C9: EMI (₹) | D9: Interest (₹) | E9: Principal (₹) | F9: Prepayment (₹) | G9: Closing Balance (₹)
A10: 1 | B10: =$E$3 -> 400000 | C10: =$E$6 -> 12813.18 | D10: =IF(B10<=0,0,ROUND(B10*$E$4/12,2)) -> 3166.67 | E10: =IF(B10<=0,0,MIN(C10-D10,B10)) -> 9646.5099 | F10: =IF(AND(A10=$B$6,B10>0),MIN($B$5,B10-E10),0) -> 0 | G10: =MAX(B10-E10-F10,0) -> 390353.49
A11: =A10+1 -> 2 | B11: =G10 -> 390353.49 | C11: =$E$6 -> 12813.18 | D11: =IF(B11<=0,0,ROUND(B11*$E$4/12,2)) -> 3090.3 | E11: =IF(B11<=0,0,MIN(C11-D11,B11)) -> 9722.8799 | F11: =IF(AND(A11=$B$6,B11>0),MIN($B$5,B11-E11),0) -> 0 | G11: =MAX(B11-E11-F11,0) -> 380630.61
A12: =A11+1 -> 3 | B12: =G11 -> 380630.61 | C12: =$E$6 -> 12813.18 | D12: =IF(B12<=0,0,ROUND(B12*$E$4/12,2)) -> 3013.33 | E12: =IF(B12<=0,0,MIN(C12-D12,B12)) -> 9799.8499 | F12: =IF(AND(A12=$B$6,B12>0),MIN($B$5,B12-E12),0) -> 0 | G12: =MAX(B12-E12-F12,0) -> 370830.76
A13: =A12+1 -> 4 | B13: =G12 -> 370830.76 | C13: =$E$6 -> 12813.18 | D13: =IF(B13<=0,0,ROUND(B13*$E$4/12,2)) -> 2935.74 | E13: =IF(B13<=0,0,MIN(C13-D13,B13)) -> 9877.4399 | F13: =IF(AND(A13=$B$6,B13>0),MIN($B$5,B13-E13),0) -> 0 | G13: =MAX(B13-E13-F13,0) -> 360953.32
A14: =A13+1 -> 5 | B14: =G13 -> 360953.32 | C14: =$E$6 -> 12813.18 | D14: =IF(B14<=0,0,ROUND(B14*$E$4/12,2)) -> 2857.55 | E14: =IF(B14<=0,0,MIN(C14-D14,B14)) -> 9955.6299 | F14: =IF(AND(A14=$B$6,B14>0),MIN($B$5,B14-E14),0) -> 0 | G14: =MAX(B14-E14-F14,0) -> 350997.69
A15: =A14+1 -> 6 | B15: =G14 -> 350997.69 | C15: =$E$6 -> 12813.18 | D15: =IF(B15<=0,0,ROUND(B15*$E$4/12,2)) -> 2778.73 | E15: =IF(B15<=0,0,MIN(C15-D15,B15)) -> 10034.45 | F15: =IF(AND(A15=$B$6,B15>0),MIN($B$5,B15-E15),0) -> 20000 | G15: =MAX(B15-E15-F15,0) -> 320963.24
A16: =A15+1 -> 7 | B16: =G15 -> 320963.24 | C16: =$E$6 -> 12813.18 | D16: =IF(B16<=0,0,ROUND(B16*$E$4/12,2)) -> 2540.96 | E16: =IF(B16<=0,0,MIN(C16-D16,B16)) -> 10272.22 | F16: =IF(AND(A16=$B$6,B16>0),MIN($B$5,B16-E16),0) -> 0 | G16: =MAX(B16-E16-F16,0) -> 310691.02
A17: =A16+1 -> 8 | B17: =G16 -> 310691.02 | C17: =$E$6 -> 12813.18 | D17: =IF(B17<=0,0,ROUND(B17*$E$4/12,2)) -> 2459.64 | E17: =IF(B17<=0,0,MIN(C17-D17,B17)) -> 10353.54 | F17: =IF(AND(A17=$B$6,B17>0),MIN($B$5,B17-E17),0) -> 0 | G17: =MAX(B17-E17-F17,0) -> 300337.48
A18: =A17+1 -> 9 | B18: =G17 -> 300337.48 | C18: =$E$6 -> 12813.18 | D18: =IF(B18<=0,0,ROUND(B18*$E$4/12,2)) -> 2377.67 | E18: =IF(B18<=0,0,MIN(C18-D18,B18)) -> 10435.51 | F18: =IF(AND(A18=$B$6,B18>0),MIN($B$5,B18-E18),0) -> 0 | G18: =MAX(B18-E18-F18,0) -> 289901.97
A19: =A18+1 -> 10 | B19: =G18 -> 289901.97 | C19: =$E$6 -> 12813.18 | D19: =IF(B19<=0,0,ROUND(B19*$E$4/12,2)) -> 2295.06 | E19: =IF(B19<=0,0,MIN(C19-D19,B19)) -> 10518.12 | F19: =IF(AND(A19=$B$6,B19>0),MIN($B$5,B19-E19),0) -> 0 | G19: =MAX(B19-E19-F19,0) -> 279383.85
A20: =A19+1 -> 11 | B20: =G19 -> 279383.85 | C20: =$E$6 -> 12813.18 | D20: =IF(B20<=0,0,ROUND(B20*$E$4/12,2)) -> 2211.79 | E20: =IF(B20<=0,0,MIN(C20-D20,B20)) -> 10601.39 | F20: =IF(AND(A20=$B$6,B20>0),MIN($B$5,B20-E20),0) -> 0 | G20: =MAX(B20-E20-F20,0) -> 268782.46
A21: =A20+1 -> 12 | B21: =G20 -> 268782.46 | C21: =$E$6 -> 12813.18 | D21: =IF(B21<=0,0,ROUND(B21*$E$4/12,2)) -> 2127.86 | E21: =IF(B21<=0,0,MIN(C21-D21,B21)) -> 10685.32 | F21: =IF(AND(A21=$B$6,B21>0),MIN($B$5,B21-E21),0) -> 0 | G21: =MAX(B21-E21-F21,0) -> 258097.14
A22: =A21+1 -> 13 | B22: =G21 -> 258097.14 | C22: =$E$6 -> 12813.18 | D22: =IF(B22<=0,0,ROUND(B22*$E$4/12,2)) -> 2043.27 | E22: =IF(B22<=0,0,MIN(C22-D22,B22)) -> 10769.91 | F22: =IF(AND(A22=$B$6,B22>0),MIN($B$5,B22-E22),0) -> 0 | G22: =MAX(B22-E22-F22,0) -> 247327.23
... A45: =A44+1 -> 36 | B45: =G44 -> 0 | C45: =$E$6 -> 12813.18 | D45: =IF(B45<=0,0,ROUND(B45*$E$4/12,2)) -> 0 | E45: =IF(B45<=0,0,MIN(C45-D45,B45)) -> 0 | F45: =IF(AND(A45=$B$6,B45>0),MIN($B$5,B45-E45),0) -> 0 | G45: =MAX(B45-E45-F45,0) -> 0
A47: Totals | D47: =SUM(D10:D45) -> 56035.08 | E47: =SUM(E10:E45) -> 380000 | F47: =SUM(F10:F45) -> 20000
A49: Months to Pay Off: | B49: =SUMPRODUCT(--(B10:B45>0)) -> 35
A50: Original Tenure (Months): | B50: =E5 -> 36
A51: Tenure Reduced By (Months): | B51: =B50-B49 -> 1
A52: Total Interest (With Prepayment) (₹): | B52: =D47 -> 56035.08
A53: Total Interest (No Prepayment) (₹): | B53: =Amortization!I1 -> 61274.47
A54: Interest Saved (₹): | B54: =B53-B52 -> 5239.39
A56: Note: EMI amount stays fixed after prepayment (tenure-reduction method), which is the default prepayment option most Indian lenders apply unless you request an EMI reduction instead.

Sheet Dashboard
A1: Two-Wheeler Loan Dashboard
A3: Best Lender (Lowest Total Cost) | D3: Lowest Total Interest (₹) | G3: Total Interest — Selected Lender (₹) | J3: Interest Saved via Prepayment (₹)
A4: =INDEX(Inputs!$G$4:$G$8,MATCH(MIN(Inputs!$J$4:$J$8),Inputs!$J$4:$J$8,0)) -> State Bank of India | D4: =MIN(Inputs!$J$4:$J$8) -> 59593.475 | G4: =Amortization!I1 -> 61274.47 | J4: ='Prepayment Simulator'!B54 -> 5239.39
A45: Selected lender for the balance and principal/interest charts is controlled from the 'Amortization' sheet dropdown (cell B3). Change it there to update these charts.
